{
  "slug": "air-max-solo-2-glass-mouthpiece-90mm",
  "name": "Air / Solo - Glass Mouthpiece 90mm",
  "brand": "Arizer",
  "category": "accessories",
  "price": 17.99,
  "image": "https://cdn.shopify.com/s/files/1/0568/8944/2473/files/Air-Max-Solo-2-Mouthpiece-straight.jpg?v=1718118060",
  "gallery": [],
  "summary": "The innovative design of the glass pod serves as both a pod and mouthpiece, making it user-friendly and easy to maintain.",
  "description": "The innovative design of the glass pod serves as both a pod and mouthpiece, making it user-friendly and easy to maintain. Its dual functionality enables precise dosing and it is environmentally conscious as it can be reused or recycled. Compatible with multiple Arizer devices including Solo 3, Solo 2 Max, Air Max, Air SE, or Solo 2 vaporiser. This mouthpiece is a versatile choice. A practical part to keep your device working as it should.",
  "specs": [],
  "inStock": true,
  "featured": false,
  "tags": [
    "accessory",
    "arizer"
  ],
  "stripeLink": "",
  "rnSku": "8161250345129",
  "order": 256
}
