{
  "slug": "extreme-q-v-tower-inner-glass-cylinder",
  "name": "Arizer Inner Glass Cylinder- Wholesale",
  "brand": "Arizer",
  "category": "accessories",
  "price": 18.95,
  "image": "https://cdn.shopify.com/s/files/1/0568/8944/2473/files/Extreme-Q-V-Tower-inner-glass-cylinder.jpg?v=1720528114",
  "gallery": [],
  "summary": "The inner glass cylinder of the Extreme Q and V-Tower Vaporiser is delicately made and may need to be replaced if broken.",
  "description": "The inner glass cylinder of the Extreme Q and V-Tower Vaporiser is delicately made and may need to be replaced if broken. Clear instructions are included with the accompanying chillum. This trusted information is sourced from the manufacturer. A practical part to keep your device working as it should.",
  "specs": [],
  "inStock": true,
  "featured": false,
  "tags": [
    "accessory",
    "arizer"
  ],
  "stripeLink": "",
  "rnSku": "8195400892585",
  "order": 287
}
